strawberry_persisted_queries/__init__.py
strawberry_persisted_queries/cache.py
strawberry_persisted_queries/django_cache/__init__.py
strawberry_persisted_queries/django_cache/cache.py
strawberry_persisted_queries/extension.py
strawberry_persisted_queries/safelisting/__init__.py
strawberry_persisted_queries/safelisting/dict.py
strawberry_persisted_queries-1.1.0.dist-info/LICENSE
strawberry_persisted_queries-1.1.0.dist-info/METADATA
strawberry_persisted_queries-1.1.0.dist-info/WHEEL
strawberry_persisted_queries-1.1.0.dist-info/RECORD
