Metadata-Version: 2.1
Name: strawberry_persisted_queries
Version: 1.1.0
Summary: Apollo-compatible persisted queries for Strawberry
Home-page: https://github.com/catgirlinspace/strawberry_persisted_queries.git
License: MIT
Author: Rosalina
Author-email: catgirl@catgirlin.space
Requires-Python: >=3.10,<4.0
Classifier: Intended Audience :: Developers
Classifier: License :: OSI Approved :: MIT License
Classifier: Programming Language :: Python :: 3
Classifier: Programming Language :: Python :: 3.10
Classifier: Programming Language :: Python :: 3.11
Classifier: Programming Language :: Python :: 3.12
Provides-Extra: django
Requires-Dist: django (>=5.0.3,<6.0.0) ; extra == "django"
Requires-Dist: strawberry-graphql (>=0.226)
Project-URL: Repository, https://github.com/catgirlinspace/strawberry_persisted_queries.git
